nibbler/__init__.py
nibbler/annotations.py
nibbler/config.py
nibbler/constants.py
nibbler/containers.py
nibbler/extension/__init__.py
nibbler/extension/constantize_globals.py
nibbler/extension/debug.py
nibbler/extension/global_to_fast.py
nibbler/extension/inline.py
nibbler/extension/integrity_check.py
nibbler/extension/map_source.py
nibbler/extension/peephole.py
nibbler/extension/precompute_conditionals.py
nibbler/util.py
nibbler-0.1.3.dist-info/LICENSE
nibbler-0.1.3.dist-info/WHEEL
nibbler-0.1.3.dist-info/METADATA
nibbler-0.1.3.dist-info/RECORD
