Metadata-Version: 2.1
Name: nibbler
Version: 0.1.3
Summary: Runtime bytecode optimizer.
Home-page: UNKNOWN
License: MIT
Author: Philip Trauner
Author-email: philip.trauner@arztpraxis.io
Requires-Python: >=3.7,<4.0
Classifier: License :: OSI Approved :: MIT License
Classifier: Programming Language :: Python :: 3
Classifier: Programming Language :: Python :: 3.7
Requires-Dist: black (>=18.9b0,<19.0)
Requires-Dist: uncompyle6 (>=3.2,<4.0)
